[
  {
    "id": "Hut",
    "layer": "Environment",
    "components": [
      {
        "type": "Transform",
        "properties": {
          "position": [ 0.0, 1.0, 0.0 ],
          "scale": [ 2.0, 2.0, 2.0 ],
          "pivot": [ 0.0, 0.0 ],
          "rotation": 0.0
        }
      },
      {
        "type": "Sprite",
        "properties": {
          "shader": "sprite_batch",
          "texture": "hut_00",
          "color": [ 1.0, 1.0, 1.0, 1.0 ]
        }
      },
      {
        "type": "Collider",
        "properties": {
          "type": "Trigger"
        }
      }
    ]
  }
]